jupyter_plz/__init__.py
jupyter_plz/jupyter_plz.py
jupyter_plz-0.1.6.dist-info/AUTHORS.rst
jupyter_plz-0.1.6.dist-info/LICENSE
jupyter_plz-0.1.6.dist-info/METADATA
jupyter_plz-0.1.6.dist-info/WHEEL
jupyter_plz-0.1.6.dist-info/top_level.txt
jupyter_plz-0.1.6.dist-info/RECORD
