Metadata-Version: 2.1
Name: jupyter-plz
Version: 0.1.6
Summary: A ChatGPT front-end for Jupyter notebooks (Copilot for Jupyter notebooks).
Home-page: https://github.com/akramz/jupyter_plz
Author: Akram Zaytar
Author-email: zaytarakram@gmail.com
License: MIT license
Keywords: jupyter_plz
Classifier: Development Status :: 2 - Pre-Alpha
Classifier: Intended Audience :: Developers
Classifier: License :: OSI Approved :: MIT License
Classifier: Natural Language :: English
Classifier: Programming Language :: Python :: 3
Classifier: Programming Language :: Python :: 3.6
Classifier: Programming Language :: Python :: 3.7
Classifier: Programming Language :: Python :: 3.8
Requires-Python: >=3.6
License-File: LICENSE
License-File: AUTHORS.rst
Requires-Dist: notebook
Requires-Dist: requests
Requires-Dist: typing
Requires-Dist: ipython
Requires-Dist: setuptools
